thename/__init__.py
thename/_utils.py
thename-1.0.3.dist-info/METADATA
thename-1.0.3.dist-info/WHEEL
thename-1.0.3.dist-info/top_level.txt
thename-1.0.3.dist-info/RECORD
